odoo8_addon_account_draft_invoice_print-8.0.1.0.0.99.dev16-py2.7-nspkg.pth
odoo8_addon_account_draft_invoice_print-8.0.1.0.0.99.dev16.dist-info/METADATA
odoo8_addon_account_draft_invoice_print-8.0.1.0.0.99.dev16.dist-info/RECORD
odoo8_addon_account_draft_invoice_print-8.0.1.0.0.99.dev16.dist-info/WHEEL
odoo8_addon_account_draft_invoice_print-8.0.1.0.0.99.dev16.dist-info/namespace_packages.txt
odoo8_addon_account_draft_invoice_print-8.0.1.0.0.99.dev16.dist-info/top_level.txt
odoo_addons/account_draft_invoice_print/README.rst
odoo_addons/account_draft_invoice_print/__init__.py
odoo_addons/account_draft_invoice_print/__openerp__.py
odoo_addons/account_draft_invoice_print/invoice_view.xml
odoo_addons/account_draft_invoice_print/i18n/account_draft_invoice_print.pot
odoo_addons/account_draft_invoice_print/i18n/de.po
odoo_addons/account_draft_invoice_print/i18n/es.po
odoo_addons/account_draft_invoice_print/i18n/fi.po
odoo_addons/account_draft_invoice_print/i18n/fr.po
odoo_addons/account_draft_invoice_print/i18n/it.po
odoo_addons/account_draft_invoice_print/i18n/ru.po
odoo_addons/account_draft_invoice_print/i18n/sl.po
odoo_addons/account_draft_invoice_print/i18n/tr.po
odoo_addons/account_draft_invoice_print/i18n/tr_TR.po
odoo_addons/account_draft_invoice_print/static/description/icon.png
